CHANGELOG.md
MANIFEST.in
README.md
setup.cfg
setup.py
versioneer.py
src/libreflow/__init__.py
src/libreflow.extensions.ligne.playblast.egg-info/PKG-INFO
src/libreflow.extensions.ligne.playblast.egg-info/SOURCES.txt
src/libreflow.extensions.ligne.playblast.egg-info/dependency_links.txt
src/libreflow.extensions.ligne.playblast.egg-info/top_level.txt
src/libreflow/extensions/__init__.py
src/libreflow/extensions/ligne/__init__.py
src/libreflow/extensions/ligne/playblast/__init__.py
src/libreflow/extensions/ligne/playblast/_version.py