Metadata-Version: 2.2
Name: libreflow.extensions.ligne.playblast
Version: 1.0.2
Home-page: https://gitlab.com/lfs.coop/libreflow/libreflow_launcher
Author: Thomas Thiebaut
Author-email: autor@les-fees-speciales.coop
License: LGPLv3+
Keywords: kabaret libreflow
Classifier: Programming Language :: Python :: 3
Classifier: Intended Audience :: Developers
Classifier: License :: OSI Approved :: GNU Lesser General Public License v3 or later (LGPLv3+)
Classifier: Operating System :: OS Independent
Requires-Python: >=3.7
Dynamic: author
Dynamic: author-email
Dynamic: classifier
Dynamic: description
Dynamic: description-content-type
Dynamic: home-page
Dynamic: keywords
Dynamic: license
Dynamic: requires-python
